ltp/__init__.py
ltp/generic.py
ltp/interface.py
ltp/legacy.py
ltp/mixin.py
ltp/module.py
ltp/nerual.py
ltp/utils.py
ltp-4.2.14.dist-info/LICENSE
ltp-4.2.14.dist-info/METADATA
ltp-4.2.14.dist-info/WHEEL
ltp-4.2.14.dist-info/top_level.txt
ltp-4.2.14.dist-info/zip-safe
ltp-4.2.14.dist-info/RECORD
