Metadata-Version: 2.1
Name: ltp
Version: 4.2.14
Summary: Language Technology Platform
Home-page: https://github.com/HIT-SCIR/ltp
Author: Yunlong Feng
Author-email: ylfeng@ir.hit.edu.cn
Classifier: Development Status :: 1 - Planning
Classifier: Operating System :: OS Independent
Classifier: Intended Audience :: Developers
Classifier: Programming Language :: Python :: 3.6
Classifier: Programming Language :: Python :: 3.7
Classifier: Programming Language :: Python :: 3.8
Classifier: Programming Language :: Python :: 3.9
Classifier: Programming Language :: Python :: 3.10
Classifier: Programming Language :: Python :: 3.11
Classifier: Topic :: Software Development :: Libraries
Requires-Python: >=3.6, <4
License-File: LICENSE
Requires-Dist: ltp-core >=0.1.3
Requires-Dist: ltp-extension >=0.1.9
Requires-Dist: huggingface-hub >=0.8.0
